kernl/__init__.py
kernl/init.py
kernl/kernl.py
kernl/lib/libkernl_c.dylib
kernl_sdk-1.0.0.dist-info/METADATA
kernl_sdk-1.0.0.dist-info/WHEEL
kernl_sdk-1.0.0.dist-info/top_level.txt
kernl_sdk-1.0.0.dist-info/RECORD
