Metadata-Version: 2.4
Name: kernl-sdk
Version: 1.0.0
Summary: Kernl SDK Python bindings
Author-email: Your Name <you@example.com>
License: MIT
Project-URL: Homepage, https://github.com/yourorg/kernl-sdk
Project-URL: Repository, https://github.com/yourorg/kernl-sdk
Classifier: Development Status :: 4 - Beta
Classifier: Intended Audience :: Developers
Classifier: License :: OSI Approved :: MIT License
Classifier: Programming Language :: Python :: 3
Classifier: Programming Language :: Python :: 3.8
Classifier: Programming Language :: Python :: 3.9
Classifier: Programming Language :: Python :: 3.10
Classifier: Programming Language :: Python :: 3.11
Classifier: Programming Language :: Python :: 3.12
Requires-Python: >=3.8
